README.md
setup.py
iosense_connect_cache/__init__.py
iosense_connect_cache/data_access.py
iosense_connect_cache.egg-info/PKG-INFO
iosense_connect_cache.egg-info/SOURCES.txt
iosense_connect_cache.egg-info/dependency_links.txt
iosense_connect_cache.egg-info/top_level.txt