Metadata-Version: 2.1
Name: iosense-connect-cache
Version: 0.0.1
Summary: iosense connect library
Author: Faclon-Labs
